AUTHORS.rst
CONTRIBUTING.rst
HISTORY.rst
LICENSE
MANIFEST.in
README.rst
setup.cfg
setup.py
create/__init__.py
create/cli.py
create/create.py
create/teszt.py
docs/Makefile
docs/authors.rst
docs/conf.py
docs/contributing.rst
docs/history.rst
docs/index.rst
docs/installation.rst
docs/make.bat
docs/readme.rst
docs/usage.rst
mcreate.egg-info/PKG-INFO
mcreate.egg-info/SOURCES.txt
mcreate.egg-info/dependency_links.txt
mcreate.egg-info/entry_points.txt
mcreate.egg-info/not-zip-safe
mcreate.egg-info/requires.txt
mcreate.egg-info/top_level.txt
tests/__init__.py
tests/test_create.py