Metadata-Version: 1.1
Name: mcreate
Version: 0.1.1
Summary: Tool to create projects
Home-page: https://github.com/matyifkbt/create
Author: Matyi
Author-email: mmatyi@caesar.elte.hu
License: MIT license
Keywords: create
Platform: UNKNOWN
Classifier: Development Status :: 2 - Pre-Alpha
Classifier: Intended Audience :: Developers
Classifier: License :: OSI Approved :: MIT License
Classifier: Natural Language :: English
Classifier: Programming Language :: Python :: 2
Classifier: Programming Language :: Python :: 2.7
Classifier: Programming Language :: Python :: 3
Classifier: Programming Language :: Python :: 3.4
Classifier: Programming Language :: Python :: 3.5
Classifier: Programming Language :: Python :: 3.6
Classifier: Programming Language :: Python :: 3.7
